geteventstore/__init__.py
geteventstore/client.py
geteventstore/event.py
geteventstore/read_stream.py
geteventstore/write_stream.py
geteventstore-0.0.4.dist-info/METADATA
geteventstore-0.0.4.dist-info/RECORD
geteventstore-0.0.4.dist-info/WHEEL
geteventstore-0.0.4.dist-info/top_level.txt
