Metadata-Version: 2.1
Name: geteventstore
Version: 0.0.4
Summary: Python HTTP Client for the Event Store API
Home-page: https://github.com/vectorhacker/pygeteventstore
Author: Victor A. Martinez Santiago
Author-email: victor@plazsa.com
License: MIT License
